husqvarna_automower_ble/__init__.py
husqvarna_automower_ble/error_codes.py
husqvarna_automower_ble/helpers.py
husqvarna_automower_ble/models.py
husqvarna_automower_ble/mower.py
husqvarna_automower_ble/protocol.json
husqvarna_automower_ble/protocol.py
husqvarna_automower_ble-1.4.2.dist-info/licenses/LICENSE
husqvarna_automower_ble-1.4.2.dist-info/METADATA
husqvarna_automower_ble-1.4.2.dist-info/WHEEL
husqvarna_automower_ble-1.4.2.dist-info/top_level.txt
husqvarna_automower_ble-1.4.2.dist-info/RECORD
