Metadata-Version: 2.4
Name: husqvarna_automower_ble
Version: 1.4.2
Summary: An unofficial reverse engineered Husqvarna Automower Connect BLE library
Author-email: Marbanz <martin.gilmozzi2005@gmail.com>, Alistair Francis <alistair@alistair23.me>
Classifier: Environment :: Console
Classifier: Programming Language :: Python :: 3.12
Classifier: License :: OSI Approved :: MIT License
Classifier: Operating System :: OS Independent
Requires-Python: >=3.12
License-File: LICENSE
Requires-Dist: bleak
Requires-Dist: bleak_retry_connector
Dynamic: license-file
